django_neat_html/__init__.py
django_neat_html/utils.py
django_neat_html-0.1.0.dist-info/LICENSE
django_neat_html-0.1.0.dist-info/METADATA
django_neat_html-0.1.0.dist-info/WHEEL
django_neat_html-0.1.0.dist-info/RECORD
