Metadata-Version: 2.1
Name: django-neat-html
Version: 0.1.0
Summary: 
Author: Sam Dudley
Author-email: dudley.co.uk@gmail.com
Requires-Python: >=3.10,<4.0
Classifier: Programming Language :: Python :: 3
Classifier: Programming Language :: Python :: 3.10
Classifier: Programming Language :: Python :: 3.11
Classifier: Programming Language :: Python :: 3.12
Requires-Dist: django (>=4.2)
Requires-Dist: neat-html (>=0.5.0,<0.6.0)
